randomstatsmodels/__init__.py
randomstatsmodels/benchmarking/__init__.py
randomstatsmodels/benchmarking/benchmarking.py
randomstatsmodels/metrics/__init__.py
randomstatsmodels/metrics/metrics.py
randomstatsmodels/models/__init__.py
randomstatsmodels/models/ensemble.py
randomstatsmodels/models/fourier.py
randomstatsmodels/models/holt_winters.py
randomstatsmodels/models/hybrid.py
randomstatsmodels/models/knn.py
randomstatsmodels/models/local_linear.py
randomstatsmodels/models/meld.py
randomstatsmodels/models/model_utils.py
randomstatsmodels/models/naive.py
randomstatsmodels/models/neo.py
randomstatsmodels/models/palf.py
randomstatsmodels/models/polymath.py
randomstatsmodels/models/rift.py
randomstatsmodels/models/ssa.py
randomstatsmodels/models/theta_ar.py
randomstatsmodels-1.6.1.dist-info/licenses/LICENSE
randomstatsmodels-1.6.1.dist-info/METADATA
randomstatsmodels-1.6.1.dist-info/WHEEL
randomstatsmodels-1.6.1.dist-info/top_level.txt
randomstatsmodels-1.6.1.dist-info/RECORD
